emb_vectors/Emb.vec
emb_vectors/__init__.py
entry.py
pretrained_model/Model.sav
pretrained_model/__init__.py
yang_ion_pred-0.1.19.dist-info/entry_points.txt
yang_ion_pred-0.1.19.dist-info/WHEEL
yang_ion_pred-0.1.19.dist-info/METADATA
yang_ion_pred-0.1.19.dist-info/RECORD
