Metadata-Version: 2.1
Name: yang-ion-pred
Version: 0.1.19
Summary: 
Author: anhttmle
Author-email: anhttmle@gmail.com
Requires-Python: >=3.6.5,<4.0.0
Classifier: Programming Language :: Python :: 3
Classifier: Programming Language :: Python :: 3.7
Classifier: Programming Language :: Python :: 3.8
Classifier: Programming Language :: Python :: 3.9
Requires-Dist: joblib (==0.15.1)
Requires-Dist: numpy (==1.14.3)
Requires-Dist: pandas (==0.23.0)
Requires-Dist: scikit-learn (==0.20.2)
